smgo_model/__init__.py
smgo_model/requerimiento.py
smgo_model/models/__init__.py
smgo_model/models/entidad.py
smgo_model/models/test.py
smgo_model-0.1.6.dist-info/METADATA
smgo_model-0.1.6.dist-info/WHEEL
smgo_model-0.1.6.dist-info/top_level.txt
smgo_model-0.1.6.dist-info/RECORD
